Metadata-Version: 2.1
Name: untitleoop
Version: 0.0.2
Summary: A package for beginnig OOP by ByllyVylly
Home-page: https://github.com/ByllyVylly/untitleoop
Author: ByllyVylly
Author-email: nabilali_p@hotmail.com
License: MIT
Download-URL: https://github.com/ByllyVylly/untitleoop/archive/refs/tags/v0.0.2.zip
Keywords: OOP,Object Oriented Program,untitle
Platform: UNKNOWN
Classifier: Development Status :: 3 - Alpha
Classifier: Intended Audience :: Education
Classifier: Topic :: Software Development :: Build Tools
Classifier: License :: OSI Approved :: MIT License
Classifier: Programming Language :: Python :: 3
Classifier: Programming Language :: Python :: 3.4
Classifier: Programming Language :: Python :: 3.5
Classifier: Programming Language :: Python :: 3.6
Classifier: Programming Language :: Python :: 3.7
Classifier: Programming Language :: Python :: 3.8
Classifier: Programming Language :: Python :: 3.9
Classifier: Programming Language :: Python :: 3.10
License-File: LICENSE
License-File: LICENSE.txt
